spud/__init__.py
spud/__main__.py
spud/api.py
spud/cli.py
spud/settings.py
spud/type.py
spud/utils.py
spud_mc-1.3.1.dist-info/LICENSE
spud_mc-1.3.1.dist-info/METADATA
spud_mc-1.3.1.dist-info/WHEEL
spud_mc-1.3.1.dist-info/entry_points.txt
spud_mc-1.3.1.dist-info/top_level.txt
spud_mc-1.3.1.dist-info/RECORD
