Metadata-Version: 2.1
Name: spud-mc
Version: 1.3.1
Summary: A Minecraft Spigot plugin manager that adheres to the Unix philosophy and Python best practices
Home-page: https://github.com/exciteabletom/spud
Author: Tommy Dougiamas
Author-email: tom@digitalnook.net
Classifier: Programming Language :: Python :: 3
Classifier: License :: OSI Approved :: GNU General Public License v3 (GPLv3)
Classifier: Development Status :: 5 - Production/Stable
Classifier: Intended Audience :: System Administrators
Classifier: Natural Language :: English
Classifier: Operating System :: OS Independent
Classifier: Topic :: System :: Software Distribution
Classifier: Typing :: Typed
Requires-Python: >=3.8
License-File: LICENSE
Requires-Dist: requests
Requires-Dist: colorama (==0.4.6)
Requires-Dist: PyYAML
Requires-Dist: emoji (==1.7.0)
Requires-Dist: beautifulsoup4
